scopemate/__init__.py
scopemate/__main__.py
scopemate/breakdown.py
scopemate/cli.py
scopemate/core.py
scopemate/engine.py
scopemate/interaction.py
scopemate/llm.py
scopemate/models.py
scopemate/storage.py
scopemate/task_analysis.py
scopemate-0.2.0.dist-info/licenses/LICENSE
scopemate-0.2.0.dist-info/METADATA
scopemate-0.2.0.dist-info/WHEEL
scopemate-0.2.0.dist-info/entry_points.txt
scopemate-0.2.0.dist-info/top_level.txt
scopemate-0.2.0.dist-info/RECORD
