Metadata-Version: 2.4
Name: scopemate
Version: 0.2.0
Summary: 🪜 A CLI tool for Purpose/Scope/Outcome planning
Author: Anoop Thomas Mathew
Author-email: Anoop Thomas Mathew <atmb4u@gmail.com>
License: MIT
Project-URL: Homepage, https://github.com/atmb4u/scopemate
Project-URL: Bug Tracker, https://github.com/atmb4u/scopemate/issues
Classifier: Programming Language :: Python :: 3
Classifier: Programming Language :: Python :: 3.10
Classifier: Programming Language :: Python :: 3.11
Classifier: Programming Language :: Python :: 3.12
Classifier: Operating System :: OS Independent
Classifier: Operating System :: Microsoft :: Windows
Classifier: Operating System :: POSIX :: Linux
Classifier: Operating System :: MacOS
Classifier: Intended Audience :: Developers
Classifier: Topic :: Software Development :: Libraries :: Python Modules
Classifier: License :: OSI Approved :: MIT License
Requires-Python: >=3.10
License-File: LICENSE
Requires-Dist: openai>=1.0.0
Requires-Dist: pydantic>=2.0.0
Requires-Dist: twine>=6.1.0
Requires-Dist: google-generativeai>=0.3.0
Requires-Dist: anthropic>=0.12.0
Requires-Dist: ipython>=8.35.0
Requires-Dist: ipdb>=0.13.13
Dynamic: author
Dynamic: license-file
Dynamic: requires-python
